mixpanel/__init__.py
mixpanel-4.10.0.dist-info/LICENSE.txt
mixpanel-4.10.0.dist-info/METADATA
mixpanel-4.10.0.dist-info/WHEEL
mixpanel-4.10.0.dist-info/top_level.txt
mixpanel-4.10.0.dist-info/RECORD
