Metadata-Version: 2.1
Name: mixpanel
Version: 4.10.0
Summary: Official Mixpanel library for Python
Home-page: https://github.com/mixpanel/mixpanel-python
Author: Mixpanel, Inc.
Author-email: dev@mixpanel.com
License: Apache
Keywords: mixpanel analytics
Classifier: License :: OSI Approved :: Apache Software License
Classifier: Operating System :: OS Independent
Classifier: Programming Language :: Python :: 2
Classifier: Programming Language :: Python :: 2.7
Classifier: Programming Language :: Python :: 3
Classifier: Programming Language :: Python :: 3.5
Classifier: Programming Language :: Python :: 3.6
Classifier: Programming Language :: Python :: 3.7
Classifier: Programming Language :: Python :: 3.8
Classifier: Programming Language :: Python :: 3.9
Classifier: Programming Language :: Python :: 3.10
Requires-Python: >=2.7, !=3.4.*
License-File: LICENSE.txt
